[
  {
    "id": "f9808690-4f36-462d-afa9-833a531cc756",
    "data": [
      {
        "text": "i lives in ",
        "userDefined": false
      },
      {
        "text": "bhuvaneshwar",
        "meta": "@place",
        "alias": "place",
        "userDefined": false
      }
    ],
    "isTemplate": false,
    "count": 0,
    "lang": "en",
    "updated": 0
  },
  {
    "id": "235a7506-6ba8-445d-83bc-23ccc9b6c269",
    "data": [
      {
        "text": "i live in ",
        "userDefined": false
      },
      {
        "text": "chidambaram",
        "meta": "@place",
        "alias": "place",
        "userDefined": false
      }
    ],
    "isTemplate": false,
    "count": 0,
    "lang": "en",
    "updated": 0
  }
]